gpt_context_builder/__init__.py
gpt_context_builder/cli.py
gpt_context_builder/server.py
gpt_context_builder/templates/index.html
gpt_context_builder-1.0.1.dist-info/LICENSE
gpt_context_builder-1.0.1.dist-info/METADATA
gpt_context_builder-1.0.1.dist-info/WHEEL
gpt_context_builder-1.0.1.dist-info/entry_points.txt
gpt_context_builder-1.0.1.dist-info/top_level.txt
gpt_context_builder-1.0.1.dist-info/RECORD
