Metadata-Version: 2.1
Name: gpt_context_builder
Version: 1.0.1
Summary: A tool to build GPT context.
Author-email: Yuichiro Masui <masui@masuidrive.jp>
License: Apache License 2.0
Project-URL: Homepage, https://github.com/masuidrive/gpt-context-builder
Project-URL: Repository, https://github.com/masuidrive/gpt-context-builder.git
Classifier: Programming Language :: Python :: 3
Classifier: License :: OSI Approved :: Apache Software License
Classifier: Operating System :: OS Independent
Requires-Python: >=3.6
License-File: LICENSE
Requires-Dist: flask>=2.0.0
Requires-Dist: pathspec>=0.9.0
Requires-Dist: tiktoken>=0.3.0
Requires-Dist: click>=8.0.0
Provides-Extra: dev
Requires-Dist: pytest>=7.0.0; extra == "dev"
Requires-Dist: pytest-cov>=4.0.0; extra == "dev"
Requires-Dist: tox>=4.0.0; extra == "dev"
Requires-Dist: black>=23.0.0; extra == "dev"
Requires-Dist: flake8>=6.0.0; extra == "dev"
Requires-Dist: isort>=5.0.0; extra == "dev"
Requires-Dist: build>=0.10.0; extra == "dev"
Requires-Dist: twine>=4.0.0; extra == "dev"
Requires-Dist: wheel>=0.40.0; extra == "dev"
